smartcell/__init__.py
fhgise_smartcell-0.0.0.dist-info/METADATA
fhgise_smartcell-0.0.0.dist-info/WHEEL
fhgise_smartcell-0.0.0.dist-info/RECORD
